[{"type":"html","input":"<header class=\"nav\">\n    <a href=\"#\" class=\"logo\">logo</a>\n    <nav class=\"tab-btn\">\n        <a class=\"active\" href=\"#home\" style=\"--clr:#ff4d4d;\">Home</a>\n        <a href=\"#about\" style=\"--clr:#c56cf0;\">About</a>\n        <a href=\"#services\" style=\"--clr:#ffeaa7;\">Services</a>\n        <a href=\"#portfolio\" style=\"--clr:#17c0eb;\">Portfolio</a>\n        <a href=\"#contact\" style=\"--clr:#fd79a8;\">Contact</a>\n    </nav>\n</header>\n<section class=\"tab\" id=\"home\" style=\"--clr:#ff4d4d;\">Home</section>\n<section class=\"tab\" id=\"about\" style=\"--clr:#c56cf0;\">About</section>\n<section class=\"tab\" id=\"services\" style=\"--clr:#ffeaa7;\">Services</section>\n<section class=\"tab\" id=\"portfolio\" style=\"--clr:#17c0eb;\">Portfolio</section>\n<section class=\"tab\" id=\"contact\" style=\"--clr:#fd79a8;\">Contact</section>"},{"type":"css","input":"@import url('https://fonts.googleapis.com/css2?family=Poppins:wght@300;400;500;600&display=swap');\n*\n{\n    margin: 0;\n    padding: 0;\n    box-sizing: border-box;\n    font-family: 'Poppins', sans-serif;\n    scroll-behavior: smooth;\n    user-select: none;\n}\n.body\n{\n    top:0;\n    opacity: 1;\n    /*background: #fff;*/\n    /*padding: 0;*/\n    /*display: inline;*/\n}\n.body > *\n{\n    display: inline;\n}\nsection.tab\n{\n    width: 100%;\n    min-height: 100vh;\n    display: flex;\n    justify-content: center;\n    align-items: center;\n    font-size: 8em;\n    font-weight: 800;\n    color: rgba(0,0,0,0.25);\n    text-transform: uppercase;\n    background: var(--clr);\n    \n}\n\nheader.nav\n{\n    position: absolute;\n    top: 0;\n    width: 100%;\n    background: #333;\n    display: flex;\n    justify-content: space-between;\n    align-items: center;\n    overflow: hidden;\n    padding: 10px 50px 0;\n}\na.logo\n{\n    position: relative;\n    color: #fff;\n    font-size: 2em;\n    font-weight: 700;\n    text-decoration: none;\n}\nheader.nav nav.tab-btn \n{\n    display: flex;\n    gap: 10px;\n}\nheader.nav nav.tab-btn a \n{\n    position: relative;\n    text-decoration: none;\n    padding: 12px 20px;\n    color: #fff;\n    font-weight: 500;\n}\nheader.nav nav.tab-btn a.active\n{\n    background: var(--clr);\n    border-top-left-radius: 10px;\n    border-top-right-radius: 10px;\n    box-shadow: 0 5px 0 0 var(--clr);\n    color: #333;\n}\nheader.nav nav.tab-btn a.active:before\n{\n    content: '';\n    position: absolute;\n    left: -20px;\n    bottom: 0;\n    width: 20px;\n    height: 20px;\n    background: #0f0;\n    border-bottom-right-radius: 20px;\n    box-shadow: 5px 5px 0 5px var(--clr);\n}\nheader.nav nav.tab-btn a.active:before\n{\n    content: '';\n    position: absolute;\n    left: -20px;\n    bottom: 0;\n    width: 20px;\n    height: 20px;\n    background: transparent;\n    border-bottom-right-radius: 20px;\n    box-shadow: 5px 5px 0 5px var(--clr);\n}\nheader.nav nav.tab-btn a.active:after\n{\n    content: '';\n    position: absolute;\n    right: -20px;\n    bottom: 0;\n    width: 20px;\n    height: 20px;\n    background: transparent;\n    border-bottom-left-radius: 20px;\n    box-shadow: -5px 5px 0 5px var(--clr);\n}\n"},{"type":"css","input":""},{"type":"js","input":"let sec = document.querySelectorAll(\"section.tab\")\nlet links = document.querySelectorAll(\"nav.tab-btn a\")\nwindow.onscroll = null;\n// window.onscroll = () =>{\nlet  window_= document.querySelector('.body > *');\nwindow_.onscroll = () =>{\n    sec.forEach( section => {\n        let top = window_.scrollTop,// scrollY\n            offset = section.offsetTop - 60,\n            height = section.offsetHeight,\n            id = section.getAttribute(\"id\");\n        \n        if(top >= offset && top < offset + height)\n        {\n            links.forEach(link =>{\n                link.classList.remove('active');\n                document.querySelector('nav.tab-btn a[href*='+id+']').classList.add('active');\n            })\n        }\n    })\n}"}]